{
  "project_info": {
    "project_number": "1043075265104",
    "project_id": "orotcode-ody",
    "storage_bucket": "orotcode-ody.appspot.com"
  },
  "client": [
    {
      "client_info": {
        "mobilesdk_app_id": "1:1043075265104:android:a8023df24843a6747c9755",
        "android_client_info": {
          "package_name": "com.orot.ody"
        }
      },
      "oauth_client": [],
      "api_key": [
        {
          "current_key": "AIzaSyD2uUOk3AjztpjiLJocZzzVPet6GPBC0Og"
        }
      ],
      "services": {
        "appinvite_service": {
          "other_platform_oauth_client": []
        }
      }
    }
  ],
  "configuration_version": "1"
}